odoo/addons/l10n_ar_account_move_tax/README.rst
odoo/addons/l10n_ar_account_move_tax/__init__.py
odoo/addons/l10n_ar_account_move_tax/__manifest__.py
odoo/addons/l10n_ar_account_move_tax/i18n/l10n_ar_account_move_tax.pot
odoo/addons/l10n_ar_account_move_tax/models/__init__.py
odoo/addons/l10n_ar_account_move_tax/models/account_move.py
odoo/addons/l10n_ar_account_move_tax/models/account_move_tax.py
odoo/addons/l10n_ar_account_move_tax/models/account_tax_group.py
odoo/addons/l10n_ar_account_move_tax/readme/CONTRIBUTORS.rst
odoo/addons/l10n_ar_account_move_tax/readme/DESCRIPTION.rst
odoo/addons/l10n_ar_account_move_tax/readme/HISTORY.rst
odoo/addons/l10n_ar_account_move_tax/security/ir.model.access.csv
odoo/addons/l10n_ar_account_move_tax/static/description/icon.png
odoo/addons/l10n_ar_account_move_tax/static/description/index.html
odoo/addons/l10n_ar_account_move_tax/views/account_move_view.xml
odoo14_addon_l10n_ar_account_move_tax-14.0.1.3.1.dev11.dist-info/METADATA
odoo14_addon_l10n_ar_account_move_tax-14.0.1.3.1.dev11.dist-info/WHEEL
odoo14_addon_l10n_ar_account_move_tax-14.0.1.3.1.dev11.dist-info/top_level.txt
odoo14_addon_l10n_ar_account_move_tax-14.0.1.3.1.dev11.dist-info/RECORD
