Metadata-Version: 2.1
Name: odoo14-addon-l10n-ar-account-move-tax
Version: 14.0.1.3.1.dev11
Summary: Account Move Tax
Home-page: https://github.com/OCA/l10n-argentina
Author: Nimarosa, ADHOC SA, Moldeo Interactive, Exemax, Codize, Odoo Community Association (OCA)
Author-email: support@odoo-community.org
License: AGPL-3
Platform: UNKNOWN
Classifier: Programming Language :: Python
Classifier: Framework :: Odoo
Classifier: Framework :: Odoo :: 14.0
Classifier: License :: OSI Approved :: GNU Affero General Public License v3
Requires-Python: >=3.6
Requires-Dist: odoo14-addon-l10n-ar-afipws
Requires-Dist: odoo (<14.1dev,>=14.0a)
